[{"id_message": 91914071692, "message": "Kim Jong-un @USER tambi\u00e9n aqu\u00ed ? ? \ud83e\udd23 \ud83d\ude05", "date": "2020-02-15 13:20:32+01:00", "platform": "Telegram"}, {"id_message": 27507741211, "message": "Klaro user 159 tu pregunta y te alludamos", "date": "2020-02-15 14:52:42+01:00", "platform": "Telegram"}, {"id_message": 10556772741, "message": "El m\u00edtico pepe ?", "date": "2020-02-17 14:14:26+01:00", "platform": "Telegram"}, {"id_message": 79957282828, "message": "Ponte a la cola xd", "date": "2020-02-18 14:54:38+01:00", "platform": "Telegram"}, {"id_message": 59543167926, "message": "Te lo digo en serio jeje , si quieres entrar manda un correo y te pones en lista de espera", "date": "2020-02-18 14:55:55+01:00", "platform": "Telegram"}, {"id_message": 17565419848, "message": "Pero tendr\u00e1s que esperar unos meses", "date": "2020-02-18 14:56:09+01:00", "platform": "Telegram"}, {"id_message": 69057894570, "message": "Ten educaci\u00f3n y saluda a tu amigo urbanG", "date": "2020-02-29 00:40:53+01:00", "platform": "Telegram"}, {"id_message": 29259198260, "message": "Tambi\u00e9n conocido como user 140 xddd", "date": "2020-02-29 00:42:27+01:00", "platform": "Telegram"}, {"id_message": 70798581198, "message": "Y el traficante m\u00e1s peligroso de Galicia", "date": "2020-02-29 00:43:52+01:00", "platform": "Telegram"}, {"id_message": 32791312497, "message": "\ud83d\ude06", "date": "2020-02-29 00:44:33+01:00", "platform": "Telegram"}, {"id_message": 57246099971, "message": "Claro seguramente , el ser amigo de el rey ayuda mucho a no ser tan corrupto", "date": "2020-02-29 00:46:06+01:00", "platform": "Telegram"}, {"id_message": 84020132197, "message": "Fue memorable haha", "date": "2020-02-29 00:49:02+01:00", "platform": "Telegram"}, {"id_message": 61233508427, "message": "Estoy de acuerdo aunque entrases , yo si que no entrar\u00eda ahora \ud83e\udd23", "date": "2020-02-29 00:51:24+01:00", "platform": "Telegram"}, {"id_message": 59345779786, "message": "Se ve que hemos madurado en este tiempo", "date": "2020-02-29 00:51:38+01:00", "platform": "Telegram"}, {"id_message": 87602087891, "message": "En que a\u00f1o vives ? ? Xddd", "date": "2020-03-05 15:20:26+01:00", "platform": "Telegram"}, {"id_message": 97429521168, "message": "60 euros una cuenta dice \ud83d\ude05", "date": "2020-03-05 15:20:39+01:00", "platform": "Telegram"}, {"id_message": 85678333850, "message": "Whattt ? ? ?", "date": "2020-03-12 15:11:44+01:00", "platform": "Telegram"}, {"id_message": 92875599013, "message": "No me creo que alguien tan tonto y perdido en este tema halla llegado a ganar tanto dinero", "date": "2020-03-12 15:12:16+01:00", "platform": "Telegram"}, {"id_message": 98434073740, "message": "En ning\u00fan momento he dicho que fueras t\u00fa , me refer\u00eda a tu amigo ...", "date": "2020-03-12 16:52:58+01:00", "platform": "Telegram"}, {"id_message": 35982907509, "message": "\ud83d\udc49 \ud83d\udc48", "date": "2020-03-22 22:31:53+01:00", "platform": "Telegram"}, {"id_message": 26193816667, "message": "En itf los mejores tipters est\u00e1n en Espa\u00f1a", "date": "2020-04-10 11:56:36+01:00", "platform": "Telegram"}, {"id_message": 12583050879, "message": "Otros deportes no se ...", "date": "2020-04-10 11:56:48+01:00", "platform": "Telegram"}, {"id_message": 37076717934, "message": "Como en Espa\u00f1a casi seguro que no xd", "date": "2020-04-10 11:57:41+01:00", "platform": "Telegram"}, {"id_message": 72891353384, "message": "No creo que la nacionalidad del Tipsters influya mucho la verdad , puede que haya deportes que beneficien por que en su pa\u00eds se siga m\u00e1s alg\u00fan deporte", "date": "2020-04-10 11:58:50+01:00", "platform": "Telegram"}, {"id_message": 99824427720, "message": "West ...", "date": "2020-04-10 11:59:03+01:00", "platform": "Telegram"}, {"id_message": 6598445328, "message": "Dime que lo de west lo dices en broma", "date": "2020-04-10 11:59:20+01:00", "platform": "Telegram"}, {"id_message": 68820855919, "message": "Me has puesto el ejemplo del mayor est\u00e1fetis de Espa\u00f1a y del Tipsters menos seguible de Espa\u00f1a ... Aqu\u00ed hay otros tipsters de Itf con numerazos", "date": "2020-04-10 12:00:10+01:00", "platform": "Telegram"}, {"id_message": 35283336283, "message": "\ud83d\ude05 \ud83d\ude05 Co\u00f1o so dec\u00edas que ven\u00eda a ayudar jaja", "date": "2020-04-10 12:03:03+01:00", "platform": "Telegram"}, {"id_message": 92997433337, "message": "Y que hace grupo privado en tuiter ?", "date": "2020-04-10 12:09:42+01:00", "platform": "Telegram"}, {"id_message": 76657940226, "message": "Yo es no uso tuiter", "date": "2020-04-10 12:09:52+01:00", "platform": "Telegram"}, {"id_message": 84695600660, "message": "15 libras no ?", "date": "2020-04-10 12:10:33+01:00", "platform": "Telegram"}, {"id_message": 67139936163, "message": "\ud83e\udd23 \ud83e\udd23", "date": "2020-04-10 12:53:09+01:00", "platform": "Telegram"}, {"id_message": 89011535021, "message": "Me acaba de abrir privado el t\u00edo ese que has puesto de estafador en el canal", "date": "2020-04-17 19:26:23+01:00", "platform": "Telegram"}, {"id_message": 13401673905, "message": "Que ha echo ese t\u00edo ?", "date": "2020-04-17 19:26:34+01:00", "platform": "Telegram"}, {"id_message": 71426708162, "message": "No si no me ha ofrecido nada es lo que extra\u00f1a xdd", "date": "2020-04-17 19:28:19+01:00", "platform": "Telegram"}, {"id_message": 72818862919, "message": "Mercadona , Carrefour y poco m\u00e1s", "date": "2020-04-17 19:30:31+01:00", "platform": "Telegram"}, {"id_message": 46158934512, "message": "Sabes que limita como Itf no ? Y que las cuotas vuelan ?", "date": "2020-04-18 11:04:12+01:00", "platform": "Telegram"}, {"id_message": 45637086713, "message": "Esa no son las stats actuales", "date": "2020-04-18 11:10:02+01:00", "platform": "Telegram"}, {"id_message": 45117386050, "message": "Ahora no verifica lo que pasa por su canal", "date": "2020-04-18 11:10:14+01:00", "platform": "Telegram"}, {"id_message": 15592475960, "message": "Jejeje asi es", "date": "2020-04-18 11:11:47+01:00", "platform": "Telegram"}, {"id_message": 85101601405, "message": "Es bueno eso no lo discuto", "date": "2020-04-18 11:13:02+01:00", "platform": "Telegram"}, {"id_message": 11404786859, "message": "Pero esto lo discuto a\u00fan menos xe", "date": "2020-04-18 11:13:15+01:00", "platform": "Telegram"}, {"id_message": 74968312313, "message": "No tanto", "date": "2020-04-18 11:13:37+01:00", "platform": "Telegram"}, {"id_message": 94777427188, "message": "He visto tirar st 5 a over 140", "date": "2020-04-18 11:13:49+01:00", "platform": "Telegram"}, {"id_message": 83113965096, "message": "Y despu\u00e9s tirar stake 10 al mismo partido a over 130", "date": "2020-04-18 11:14:10+01:00", "platform": "Telegram"}, {"id_message": 35517513908, "message": "Y rojear los 2 \ud83e\udd23 \ud83e\udd23 \ud83e\udd23", "date": "2020-04-18 11:14:20+01:00", "platform": "Telegram"}, {"id_message": 34917986518, "message": "No te f\u00edes de esas stats", "date": "2020-04-18 11:15:39+01:00", "platform": "Telegram"}, {"id_message": 28097010592, "message": "Podr\u00edamos pillar a DiositoLoL", "date": "2020-04-18 11:48:38+01:00", "platform": "Telegram"}, {"id_message": 74128077779, "message": "Es el mejor", "date": "2020-04-18 11:50:51+01:00", "platform": "Telegram"}, {"id_message": 18829059495, "message": "Va quien se une para pillar a DiositoLoL", "date": "2020-04-20 19:07:49+01:00", "platform": "Telegram"}, {"id_message": 35957069342, "message": "Los que me hab\u00e9is preguntado , yo es que no tengo su contacto", "date": "2020-04-20 20:34:17+01:00", "platform": "Telegram"}, {"id_message": 31839967106, "message": "No , pasa su contacto", "date": "2020-04-20 22:20:31+01:00", "platform": "Telegram"}, {"id_message": 25986926687, "message": "500 dicen", "date": "2020-04-20 22:38:31+01:00", "platform": "Telegram"}, {"id_message": 10314170663, "message": "Cuanto vale ?", "date": "2020-04-20 22:38:42+01:00", "platform": "Telegram"}, {"id_message": 13490174725, "message": "Pasala t\u00edo", "date": "2020-04-20 22:49:57+01:00", "platform": "Telegram"}, {"id_message": 10405824763, "message": "Propagandolo en grupos de 500 personas os deveria durar menos a\u00fan xd", "date": "2020-04-22 10:24:09+01:00", "platform": "Telegram"}, {"id_message": 49743277318, "message": "A mi no me sale el mismo s\u00edmbolo tamooco xd", "date": "2020-04-23 19:24:15+01:00", "platform": "Telegram"}, {"id_message": 45323775097, "message": "Que hace el pesao este aqu\u00ed dios", "date": "2020-04-27 11:58:13+01:00", "platform": "Telegram"}, {"id_message": 4325393631, "message": "No se de donde sale este t\u00edo pero esta por todos los grupos", "date": "2020-04-27 19:22:30+01:00", "platform": "Telegram"}, {"id_message": 79573568347, "message": "This !", "date": "2020-05-22 14:52:00+01:00", "platform": "Telegram"}, {"id_message": 23204645089, "message": "Yo no ten\u00eda ni idea de eso que dec\u00eds , y la verdad lo ten\u00eda pendiente para probar alg\u00fan d\u00eda . Pero si es as\u00ed eso , la verdad que no voy dar mi dinero a alguien que sea tan sectarista ... El trabajo es una cosa y la ideolog\u00eda otra", "date": "2020-05-22 14:53:26+01:00", "platform": "Telegram"}, {"id_message": 1013546253, "message": "No est\u00e1 subiendo los picks a bloga no ?", "date": "2020-05-29 14:49:18+01:00", "platform": "Telegram"}, {"id_message": 88551310468, "message": "Pues te van a volar las cuentas as\u00ed", "date": "2020-05-29 14:49:58+01:00", "platform": "Telegram"}, {"id_message": 25615964545, "message": "Si no es mucho yo", "date": "2020-05-30 16:19:23+01:00", "platform": "Telegram"}, {"id_message": 74193242103, "message": "Ah nada no vi que ya lo solucionaste xd", "date": "2020-05-30 16:19:42+01:00", "platform": "Telegram"}, {"id_message": 25501658495, "message": "Hola", "date": "2018-11-08 20:00:04+01:00", "platform": "Telegram"}, {"id_message": 98411718554, "message": "De que trata este grupo ?", "date": "2018-11-08 20:00:08+01:00", "platform": "Telegram"}, {"id_message": 95230196906, "message": "Sean buenos", "date": "2018-11-08 20:52:50+01:00", "platform": "Telegram"}, {"id_message": 90652949940, "message": "Y cuales son sus favoritas ?", "date": "2018-11-08 21:09:28+01:00", "platform": "Telegram"}, {"id_message": 38630164577, "message": "Woo", "date": "2018-11-08 21:10:04+01:00", "platform": "Telegram"}, {"id_message": 16963727376, "message": "Sois muy guais todos aqu\u00ed ;)", "date": "2018-11-08 21:10:28+01:00", "platform": "Telegram"}, {"id_message": 26522610495, "message": "Llamar a la @USER que lo manden a la c\u00e1rcel", "date": "2018-11-09 08:04:00+01:00", "platform": "Telegram"}, {"id_message": 46961976138, "message": "200 euros no majo ?", "date": "2018-11-09 23:29:47+01:00", "platform": "Telegram"}, {"id_message": 65212443758, "message": "Tienes 200 euros que perder , como que nada \ud83d\ude02", "date": "2018-11-09 23:30:11+01:00", "platform": "Telegram"}, {"id_message": 3830760923, "message": "Lidl ? ? ?", "date": "2018-11-09 23:33:54+01:00", "platform": "Telegram"}, {"id_message": 1437744767, "message": "Eso que co\u00f1o es ?", "date": "2018-11-09 23:34:01+01:00", "platform": "Telegram"}, {"id_message": 59797166564, "message": "Ya lo se", "date": "2018-11-09 23:34:29+01:00", "platform": "Telegram"}, {"id_message": 22265035260, "message": "Y Lidl hace un reto ? \ud83e\udd37\u200d\u2642", "date": "2018-11-09 23:34:43+01:00", "platform": "Telegram"}, {"id_message": 94614372569, "message": "Rust\u00ed ?", "date": "2018-11-11 21:44:26+01:00", "platform": "Telegram"}, {"id_message": 79007584943, "message": "Eres tu ?", "date": "2018-11-11 21:44:50+01:00", "platform": "Telegram"}, {"id_message": 17794210976, "message": "A toro pasado ...", "date": "2018-11-11 22:58:46+01:00", "platform": "Telegram"}, {"id_message": 5456074589, "message": "Alguien tiene a mano el tel\u00e9fono de user 3714 Hill ?", "date": "2018-11-11 22:59:00+01:00", "platform": "Telegram"}, {"id_message": 94630567707, "message": "Yo creo que se refiere a cadena de tipster", "date": "2018-11-13 10:45:33+01:00", "platform": "Telegram"}, {"id_message": 57458215688, "message": "\ud83d\ude02 \ud83d\ude02", "date": "2018-11-15 10:44:35+01:00", "platform": "Telegram"}, {"id_message": 18513513963, "message": "Pues yo no tuve problemas nunca con codere", "date": "2018-11-15 10:45:08+01:00", "platform": "Telegram"}, {"id_message": 89583012227, "message": "Me hace gracia que alguno dig\u00e1is que las bookies son estafadores , cuando vosotros est\u00e1is suplantando identidad para registraros en esa casa \ud83d\ude05", "date": "2018-11-15 10:46:02+01:00", "platform": "Telegram"}, {"id_message": 8863199265, "message": "Si yo soi Sevilla para que voi a firmar ? \ud83d\ude02", "date": "2018-11-22 14:51:19+01:00", "platform": "Telegram"}, {"id_message": 36555362670, "message": "Por algo ser\u00e1 ...", "date": "2018-11-24 13:55:02+01:00", "platform": "Telegram"}, {"id_message": 39112353887, "message": "Pues que va a pasar que solo puedes solicitar un bono por cada residencia ... De cabrones nada , solo cumplen con la ley \ud83d\ude02", "date": "2018-11-24 13:57:18+01:00", "platform": "Telegram"}, {"id_message": 35906496510, "message": "Es posible que si es as\u00ed no recuperes el bono", "date": "2018-11-24 13:57:52+01:00", "platform": "Telegram"}, {"id_message": 69554685245, "message": "@USER deja de hacer spam por privado colega", "date": "2018-12-17 21:21:47+01:00", "platform": "Telegram"}, {"id_message": 98510001741, "message": "user 4652 tiene invi para forocoches ?", "date": "2018-12-21 19:17:12+01:00", "platform": "Telegram"}, {"id_message": 2076397935, "message": "Yo quiero invi para fc", "date": "2018-12-29 12:38:32+01:00", "platform": "Telegram"}, {"id_message": 10821132573, "message": "Alguien vende ?", "date": "2018-12-29 12:38:37+01:00", "platform": "Telegram"}, {"id_message": 4188463070, "message": "O como la consigo ?", "date": "2018-12-29 12:38:42+01:00", "platform": "Telegram"}, {"id_message": 78103217032, "message": "Jqjaja", "date": "2019-01-26 16:05:10+01:00", "platform": "Telegram"}, {"id_message": 29365448470, "message": "Me borran los mensajes ?", "date": "2019-01-26 16:05:17+01:00", "platform": "Telegram"}, {"id_message": 87865764045, "message": "Y a ti por que te dejan decir eso y a mi no ? \ud83d\ude02", "date": "2019-01-26 16:06:14+01:00", "platform": "Telegram"}, {"id_message": 77923745120, "message": "Puffff", "date": "2019-01-26 16:06:31+01:00", "platform": "Telegram"}, {"id_message": 40617873399, "message": "Esto es un grupo de televenta macho", "date": "2019-01-26 16:06:42+01:00", "platform": "Telegram"}, {"id_message": 68067933138, "message": "VAMOS user 3747 \u2757 \ufe0f \ud83d\udca5 INI_HASHTAG Startbet END_HASHTAG \ud83c\uddea\ud83c\uddf8 \ud83d\udd39 Ll\u00e9vate 199 \u20ac SIN RIESGO si user 1163 Nadal gana la final \u2757 \ufe0f \ud83d\udca5 \u2728 Junto a user 1267 y Startbet organizamos esta apuesta SIN RIESGO , en la que si user 1163 no gana , te devolvemos lo apostado a tu Paypal . Y si user 1163 gana ma\u00f1ana la final a Djokovic nos llevamos 99 \u20ac retirables y 100 \u20ac en freebets , que con apostarlas una vez ya podemos retirar ganancias . Adem\u00e1s de regalos seguros como invitaciones a user 1267 y 1 a\u00f1o gratis de Startbet Premium . \u2757 \ufe0fS\u00f3lo nuevos usuarios , si ya tienes cuenta en la casa de uno de los pasos , s\u00e1ltate ese paso y completa los otros : 1\ufe0f\u20e3 Reg\u00edstrate AQU\u00cd con c\u00f3digo PRO 2019 y deposita 20 \u20ac ( sin aceptar ning\u00fan bono de bienvenida ) luego introduce el c\u00f3digo REDAPUESTAS aqu\u00ed . Finalmente apuesta los 20 \u20ac a user 1163.2 \ufe0f\u20e3 Reg\u00edstrate AQU\u00cd y deposita 10 \u20ac . Haz apuesta de 5 \u20ac a que user 1163 gana con supercuota , y luego otra de 5 \u20ac normal a que user 1163 gana . 3\ufe0f\u20e3 Reg\u00edstrate AQU\u00cd . Luego , acepta el bono en Aprovechar ahora . Deposita y apuesta 20 \u20ac a user 11634\ufe0f\u20e3 Una vez completado los pasos anteriores , Rellena este formulario para los regalos y devoluciones.Si apuestas en las 3 casas , te llevar\u00edas lo siguiente , si lo haces s\u00f3lo en alguna / s comprueba aqu\u00ed las ganancias : \ud83d\udc4d SI user 3747 GANA \ud83d\udd25 99 \u20ac retirables en el acto \ud83d\udd25 100 \u20ac Freebet , retirables al apostar una vez . \ud83d\udc4e SI NO GANA \ud83d\udcb6 Te devolvemos tus 50 \u20ac en Paypal o cheque Amazon \ud83d\udcb6 30 \u20ac en Freebet , retirables al apostar una vez . \ud83d\udcaa + REGALOS SEGUROS \ud83c\udf81 + 3 invitaciones a user 1267 \ud83c\udf81 + 1 Startbet Premium 2020 \ud83d\udc8e Opcional : 40 \u20ac EXTRA en m\u00e1s freebets \ud83c\udf84 Chollometro.com \ud83c\udf85\ud83c\udffb @USER / @USER / @USER", "date": "2019-01-26 16:07:14+01:00", "platform": "Telegram"}, {"id_message": 27370644746, "message": "Madre mia , 5 euros te pasaste un poco no ? \ud83d\ude02", "date": "2019-02-04 17:40:13+01:00", "platform": "Telegram"}, {"id_message": 9402715766, "message": "Que te piensas que estas vendiendo entradas para la pacha ? ? Esperando puedes quedarte mozito \ud83d\ude02", "date": "2019-02-04 19:58:47+01:00", "platform": "Telegram"}, {"id_message": 27354263947, "message": "El cielo y el sueldo ... user 4652 se lucra de algo su trabajo debe de tener ... Tampoco lo esperen y encima f\u00e1cil xd", "date": "2019-02-05 21:32:48+01:00", "platform": "Telegram"}, {"id_message": 56721395627, "message": "Tiene stats ? No se como puedes estar tan seguro de eso", "date": "2019-03-12 10:45:09+01:00", "platform": "Telegram"}, {"id_message": 95126680612, "message": "Eeeeeeeeeeee \ud83d\udc4b \ud83d\udc4b \ud83d\udc4b", "date": "2019-03-25 22:12:51+01:00", "platform": "Telegram"}, {"id_message": 56308161478, "message": "Pues si tu eres quien yo creo , si lo ser\u00e9 \ud83e\udd37\u200d\u2642", "date": "2019-03-25 22:15:39+01:00", "platform": "Telegram"}, {"id_message": 20419488842, "message": "Se marcho mi socio ? Oooo lo largasteis ? ?", "date": "2019-03-30 12:04:47+01:00", "platform": "Telegram"}]