[{"id_message": 59014641524, "message": "unknown me mandas un saludo", "date": "2022-02-26 18:22:08+01:00", "platform": "Twitch"}, {"id_message": 65183143998, "message": "hoy se viene cuchillo", "date": "2022-02-26 18:22:08+01:00", "platform": "Twitch"}, {"id_message": 68951799286, "message": "f", "date": "2022-02-26 18:22:08+01:00", "platform": "Twitch"}, {"id_message": 33840562425, "message": "jajajajajajaj", "date": "2022-02-26 18:22:08+01:00", "platform": "Twitch"}, {"id_message": 37919334022, "message": "unknown cuando un siteries pierdes ? ? ?", "date": "2022-02-26 18:22:09+01:00", "platform": "Twitch"}, {"id_message": 69447654190, "message": "cuando hay si te ries pierdes", "date": "2022-02-26 18:22:09+01:00", "platform": "Twitch"}, {"id_message": 12300095547, "message": "xd", "date": "2022-02-26 18:22:09+01:00", "platform": "Twitch"}, {"id_message": 18926458018, "message": "si te ries pierdes", "date": "2022-02-26 18:22:09+01:00", "platform": "Twitch"}]